mongoengine_datatables/__init__.py
mongoengine_datatables/serverside_datatables.py
mongoengine_datatables-0.1.2.dist-info/LICENSE
mongoengine_datatables-0.1.2.dist-info/WHEEL
mongoengine_datatables-0.1.2.dist-info/METADATA
mongoengine_datatables-0.1.2.dist-info/RECORD
