Metadata-Version: 2.1
Name: mongoengine_datatables
Version: 0.1.2
Summary: import
Home-page: https://github.com/Alexmod/mongoengine_datatables
License: UNKNOWN
Author: __token__
Author-email: alexmod@protonmail.com
Requires-Python: >=3.6
Classifier: License :: OSI Approved :: MIT License
